oscars.py
settings.py
competicion-0.0.2.dist-info/METADATA
competicion-0.0.2.dist-info/WHEEL
competicion-0.0.2.dist-info/RECORD
