Metadata-Version: 2.1
Name: competicion
Version: 0.0.2
Summary: My customized ORM on Sales
Project-URL: Homepage, https://github.com/Junhao42/competicion
Project-URL: Bug Tracker, https://github.com/Junhao42/competicion/issues
Author-email: junhe42 <junhao91102@gmail.com>
Classifier: License :: OSI Approved :: MIT License
Classifier: Operating System :: OS Independent
Classifier: Programming Language :: Python :: 3
Requires-Python: >=3.9
